{
	"name": "Game",
	"layers": [
		{
			"name": "Static",
			"overriden": 0,
			"subLayers": [],
			"instances": [],
			"sid": 894218950625311,
			"effectTypes": [],
			"isInitiallyVisible": true,
			"isInitiallyInteractive": true,
			"color": [
				1,
				1,
				1,
				1
			],
			"backgroundColor": [
				0.3686274509803922,
				0.3686274509803922,
				0.3686274509803922,
				1
			],
			"isTransparent": true,
			"parallaxX": 0,
			"parallaxY": 0,
			"scaleRate": 1,
			"forceOwnTexture": false,
			"renderingMode": "3d",
			"drawOrder": "z-order",
			"useRenderCells": false,
			"blendMode": "normal",
			"zElevation": 0,
			"global": false
		},
		{
			"name": "Stage",
			"overriden": 0,
			"subLayers": [
				{
					"name": "Parallax2",
					"overriden": 0,
					"subLayers": [],
					"instances": [],
					"sid": 515264682177248,
					"effectTypes": [],
					"isInitiallyVisible": true,
					"isInitiallyInteractive": true,
					"color": [
						1,
						1,
						1,
						1
					],
					"backgroundColor": [
						0.3686274509803922,
						0.3686274509803922,
						0.3686274509803922,
						1
					],
					"isTransparent": true,
					"parallaxX": 0.75,
					"parallaxY": 0.6,
					"scaleRate": 1,
					"forceOwnTexture": false,
					"renderingMode": "3d",
					"drawOrder": "z-order",
					"useRenderCells": false,
					"blendMode": "normal",
					"zElevation": 0,
					"global": false
				},
				{
					"name": "Parallax1",
					"overriden": 0,
					"subLayers": [],
					"instances": [],
					"sid": 657417239853853,
					"effectTypes": [],
					"isInitiallyVisible": true,
					"isInitiallyInteractive": true,
					"color": [
						1,
						1,
						1,
						1
					],
					"backgroundColor": [
						0.3686274509803922,
						0.3686274509803922,
						0.3686274509803922,
						1
					],
					"isTransparent": true,
					"parallaxX": 0.85,
					"parallaxY": 0.8,
					"scaleRate": 1,
					"forceOwnTexture": false,
					"renderingMode": "3d",
					"drawOrder": "z-order",
					"useRenderCells": false,
					"blendMode": "normal",
					"zElevation": 0,
					"global": false
				}
			],
			"instances": [
				{
					"type": "stage_Backgrounds",
					"properties": {
						"initially-visible": true,
						"initial-animation": "Roots",
						"initial-frame": 0,
						"enable-collisions": true,
						"live-preview": false
					},
					"uid": 74,
					"instanceVariables": {},
					"behaviors": {},
					"world": {
						"x": 0,
						"y": 0,
						"width": 640,
						"height": 360,
						"originX": 0,
						"originY": 0,
						"color": [
							1,
							1,
							1,
							1
						],
						"angle": 0,
						"zElevation": 0
					}
				},
				{
					"type": "misc_GameController",
					"properties": {
						"initially-visible": true,
						"initial-animation": "Animation 1",
						"initial-frame": 0,
						"enable-collisions": true,
						"live-preview": false
					},
					"uid": 49,
					"instanceVariables": {},
					"behaviors": {
						"Tween": {
							"properties": {
								"enabled": true
							}
						},
						"Timer": {
							"properties": {}
						}
					},
					"world": {
						"x": 0,
						"y": -16,
						"width": 16,
						"height": 16,
						"originX": 0.5,
						"originY": 0.5,
						"color": [
							1,
							1,
							1,
							1
						],
						"angle": 0,
						"zElevation": 0
					}
				}
			],
			"sid": 743925072616038,
			"effectTypes": [],
			"isInitiallyVisible": true,
			"isInitiallyInteractive": true,
			"color": [
				1,
				1,
				1,
				1
			],
			"backgroundColor": [
				0.3686274509803922,
				0.3686274509803922,
				0.3686274509803922,
				1
			],
			"isTransparent": true,
			"parallaxX": 1,
			"parallaxY": 1,
			"scaleRate": 1,
			"forceOwnTexture": false,
			"renderingMode": "3d",
			"drawOrder": "z-order",
			"useRenderCells": false,
			"blendMode": "normal",
			"zElevation": 0,
			"global": false
		},
		{
			"name": "Solid",
			"overriden": 0,
			"subLayers": [],
			"instances": [],
			"sid": 360171613702159,
			"effectTypes": [],
			"isInitiallyVisible": true,
			"isInitiallyInteractive": true,
			"color": [
				1,
				1,
				1,
				1
			],
			"backgroundColor": [
				0.3686274509803922,
				0.3686274509803922,
				0.3686274509803922,
				1
			],
			"isTransparent": true,
			"parallaxX": 1,
			"parallaxY": 1,
			"scaleRate": 1,
			"forceOwnTexture": false,
			"renderingMode": "3d",
			"drawOrder": "z-order",
			"useRenderCells": false,
			"blendMode": "normal",
			"zElevation": 0,
			"global": false
		},
		{
			"name": "Game",
			"overriden": 0,
			"subLayers": [],
			"instances": [
				{
					"type": "pla_Player",
					"properties": {
						"initially-visible": false,
						"initial-animation": "Animation 1",
						"initial-frame": 0,
						"enable-collisions": true,
						"live-preview": false
					},
					"uid": 19,
					"instanceVariables": {
						"input": "Keyboard",
						"character": "Jack",
						"jumps": 2,
						"jumps_max": 2,
						"char_UID": 0,
						"player_ID": 0,
						"step_UID": 0,
						"vertical_direction": "",
						"horizontal_direction": "",
						"attacking": false,
						"variable_x": 0,
						"variable_y": 0,
						"hp_percentage": 0,
						"hitstun_timer": 0,
						"can_move": false,
						"can_attack": false,
						"knockbackX_tween_destination": 0,
						"knockbackY_tween_destination": 0,
						"jump_buffered": false,
						"attack_buffered": "",
						"onair_timer": 0,
						"jump_short": false,
						"can_upspecial": true,
						"can_downspecial": true,
						"can_sidespecial": true,
						"loaded": false
					},
					"behaviors": {
						"Platform": {
							"properties": {
								"max-speed": 100,
								"acceleration": 1500,
								"deceleration": 1500,
								"jump-strength": 400,
								"gravity": 1500,
								"max-fall-speed": 100,
								"double-jump": false,
								"jump-sustain": 0,
								"default-controls": false,
								"enabled": true
							}
						},
						"Pin": {
							"properties": {
								"destroy": false
							}
						},
						"Tween": {
							"properties": {
								"enabled": true
							}
						},
						"Sine": {
							"properties": {
								"movement": "horizontal",
								"wave": "triangle",
								"period": 0.02,
								"period-random": 0.03,
								"period-offset": 0,
								"period-offset-random": 0,
								"magnitude": 1,
								"magnitude-random": 1,
								"enabled": false,
								"live-preview": false
							}
						},
						"Sine2": {
							"properties": {
								"movement": "vertical",
								"wave": "triangle",
								"period": 0.02,
								"period-random": 0.03,
								"period-offset": 0,
								"period-offset-random": 0,
								"magnitude": 1,
								"magnitude-random": 1,
								"enabled": false,
								"live-preview": false
							}
						},
						"Timer": {
							"properties": {}
						}
					},
					"world": {
						"x": 496,
						"y": 256,
						"width": 16,
						"height": 16,
						"originX": 0.5,
						"originY": 1,
						"color": [
							1,
							1,
							1,
							1
						],
						"angle": 0,
						"zElevation": 0
					}
				},
				{
					"type": "misc_Camera",
					"properties": {
						"initially-visible": false,
						"initial-animation": "Animation 1",
						"initial-frame": 0,
						"enable-collisions": true,
						"live-preview": false
					},
					"uid": 37,
					"instanceVariables": {},
					"behaviors": {
						"ScrollTo": {
							"properties": {
								"enabled": true
							}
						},
						"Tween": {
							"properties": {
								"enabled": true
							}
						}
					},
					"world": {
						"x": 305.3213330977368,
						"y": 211.16857169185033,
						"width": 16,
						"height": 16,
						"originX": 0.5,
						"originY": 0.5,
						"color": [
							1,
							1,
							1,
							1
						],
						"angle": 0,
						"zElevation": 0
					}
				},
				{
					"type": "pla_Player",
					"properties": {
						"initially-visible": false,
						"initial-animation": "Animation 1",
						"initial-frame": 0,
						"enable-collisions": true,
						"live-preview": false
					},
					"uid": 40,
					"instanceVariables": {
						"input": "Gamepad0",
						"character": "Balldemon",
						"jumps": 2,
						"jumps_max": 2,
						"char_UID": 0,
						"player_ID": 0,
						"step_UID": 0,
						"vertical_direction": "",
						"horizontal_direction": "",
						"attacking": false,
						"variable_x": 0,
						"variable_y": 0,
						"hp_percentage": 0,
						"hitstun_timer": 0,
						"can_move": false,
						"can_attack": false,
						"knockbackX_tween_destination": 0,
						"knockbackY_tween_destination": 0,
						"jump_buffered": false,
						"attack_buffered": "",
						"onair_timer": 0,
						"jump_short": false,
						"can_upspecial": true,
						"can_downspecial": true,
						"can_sidespecial": true,
						"loaded": false
					},
					"behaviors": {
						"Platform": {
							"properties": {
								"max-speed": 100,
								"acceleration": 1500,
								"deceleration": 1500,
								"jump-strength": 400,
								"gravity": 1500,
								"max-fall-speed": 100,
								"double-jump": false,
								"jump-sustain": 0,
								"default-controls": false,
								"enabled": true
							}
						},
						"Pin": {
							"properties": {
								"destroy": false
							}
						},
						"Tween": {
							"properties": {
								"enabled": true
							}
						},
						"Sine": {
							"properties": {
								"movement": "horizontal",
								"wave": "triangle",
								"period": 0.02,
								"period-random": 0.03,
								"period-offset": 0,
								"period-offset-random": 0,
								"magnitude": 1,
								"magnitude-random": 1,
								"enabled": false,
								"live-preview": false
							}
						},
						"Sine2": {
							"properties": {
								"movement": "vertical",
								"wave": "triangle",
								"period": 0.02,
								"period-random": 0.03,
								"period-offset": 0,
								"period-offset-random": 0,
								"magnitude": 1,
								"magnitude-random": 1,
								"enabled": false,
								"live-preview": false
							}
						},
						"Timer": {
							"properties": {}
						}
					},
					"world": {
						"x": 128,
						"y": 144,
						"width": 16,
						"height": 16,
						"originX": 0.5,
						"originY": 1,
						"color": [
							1,
							1,
							1,
							1
						],
						"angle": 0,
						"zElevation": 0
					}
				},
				{
					"type": "pla_Player",
					"properties": {
						"initially-visible": false,
						"initial-animation": "Animation 1",
						"initial-frame": 0,
						"enable-collisions": true,
						"live-preview": false
					},
					"uid": 38,
					"instanceVariables": {
						"input": "Gamepad1",
						"character": "Gornom",
						"jumps": 2,
						"jumps_max": 2,
						"char_UID": 0,
						"player_ID": 0,
						"step_UID": 0,
						"vertical_direction": "",
						"horizontal_direction": "",
						"attacking": false,
						"variable_x": 0,
						"variable_y": 0,
						"hp_percentage": 0,
						"hitstun_timer": 0,
						"can_move": false,
						"can_attack": false,
						"knockbackX_tween_destination": 0,
						"knockbackY_tween_destination": 0,
						"jump_buffered": false,
						"attack_buffered": "",
						"onair_timer": 0,
						"jump_short": false,
						"can_upspecial": true,
						"can_downspecial": true,
						"can_sidespecial": true,
						"loaded": false
					},
					"behaviors": {
						"Platform": {
							"properties": {
								"max-speed": 100,
								"acceleration": 1500,
								"deceleration": 1500,
								"jump-strength": 400,
								"gravity": 1500,
								"max-fall-speed": 100,
								"double-jump": false,
								"jump-sustain": 0,
								"default-controls": false,
								"enabled": true
							}
						},
						"Pin": {
							"properties": {
								"destroy": false
							}
						},
						"Tween": {
							"properties": {
								"enabled": true
							}
						},
						"Sine": {
							"properties": {
								"movement": "horizontal",
								"wave": "triangle",
								"period": 0.02,
								"period-random": 0.03,
								"period-offset": 0,
								"period-offset-random": 0,
								"magnitude": 1,
								"magnitude-random": 1,
								"enabled": false,
								"live-preview": false
							}
						},
						"Sine2": {
							"properties": {
								"movement": "vertical",
								"wave": "triangle",
								"period": 0.02,
								"period-random": 0.03,
								"period-offset": 0,
								"period-offset-random": 0,
								"magnitude": 1,
								"magnitude-random": 1,
								"enabled": false,
								"live-preview": false
							}
						},
						"Timer": {
							"properties": {}
						}
					},
					"world": {
						"x": 400,
						"y": 256,
						"width": 16,
						"height": 16,
						"originX": 0.5,
						"originY": 1,
						"color": [
							1,
							1,
							1,
							1
						],
						"angle": 0,
						"zElevation": 0
					}
				},
				{
					"type": "pla_Player",
					"properties": {
						"initially-visible": false,
						"initial-animation": "Animation 1",
						"initial-frame": 0,
						"enable-collisions": true,
						"live-preview": false
					},
					"uid": 41,
					"instanceVariables": {
						"input": "Gamepad2",
						"character": "Marcos3D",
						"jumps": 2,
						"jumps_max": 2,
						"char_UID": 0,
						"player_ID": 0,
						"step_UID": 0,
						"vertical_direction": "",
						"horizontal_direction": "",
						"attacking": false,
						"variable_x": 0,
						"variable_y": 0,
						"hp_percentage": 0,
						"hitstun_timer": 0,
						"can_move": false,
						"can_attack": false,
						"knockbackX_tween_destination": 0,
						"knockbackY_tween_destination": 0,
						"jump_buffered": false,
						"attack_buffered": "",
						"onair_timer": 0,
						"jump_short": false,
						"can_upspecial": true,
						"can_downspecial": true,
						"can_sidespecial": true,
						"loaded": false
					},
					"behaviors": {
						"Platform": {
							"properties": {
								"max-speed": 100,
								"acceleration": 1500,
								"deceleration": 1500,
								"jump-strength": 400,
								"gravity": 1500,
								"max-fall-speed": 100,
								"double-jump": false,
								"jump-sustain": 0,
								"default-controls": false,
								"enabled": true
							}
						},
						"Pin": {
							"properties": {
								"destroy": false
							}
						},
						"Tween": {
							"properties": {
								"enabled": true
							}
						},
						"Sine": {
							"properties": {
								"movement": "horizontal",
								"wave": "triangle",
								"period": 0.02,
								"period-random": 0.03,
								"period-offset": 0,
								"period-offset-random": 0,
								"magnitude": 1,
								"magnitude-random": 1,
								"enabled": false,
								"live-preview": false
							}
						},
						"Sine2": {
							"properties": {
								"movement": "vertical",
								"wave": "triangle",
								"period": 0.02,
								"period-random": 0.03,
								"period-offset": 0,
								"period-offset-random": 0,
								"magnitude": 1,
								"magnitude-random": 1,
								"enabled": false,
								"live-preview": false
							}
						},
						"Timer": {
							"properties": {}
						}
					},
					"world": {
						"x": 224,
						"y": 176,
						"width": 16,
						"height": 16,
						"originX": 0.5,
						"originY": 1,
						"color": [
							1,
							1,
							1,
							1
						],
						"angle": 0,
						"zElevation": 0
					}
				}
			],
			"sid": 566506966648129,
			"effectTypes": [],
			"isInitiallyVisible": true,
			"isInitiallyInteractive": true,
			"color": [
				1,
				1,
				1,
				1
			],
			"backgroundColor": [
				0.3686274509803922,
				0.3686274509803922,
				0.3686274509803922,
				1
			],
			"isTransparent": true,
			"parallaxX": 1,
			"parallaxY": 1,
			"scaleRate": 1,
			"forceOwnTexture": false,
			"renderingMode": "3d",
			"drawOrder": "z-order",
			"useRenderCells": false,
			"blendMode": "normal",
			"zElevation": 0,
			"global": false
		},
		{
			"name": "Lighting",
			"overriden": 0,
			"subLayers": [],
			"instances": [],
			"sid": 522332594365413,
			"effectTypes": [],
			"isInitiallyVisible": true,
			"isInitiallyInteractive": true,
			"color": [
				1,
				1,
				1,
				1
			],
			"backgroundColor": [
				0.3686274509803922,
				0.3686274509803922,
				0.3686274509803922,
				1
			],
			"isTransparent": true,
			"parallaxX": 1,
			"parallaxY": 1,
			"scaleRate": 1,
			"forceOwnTexture": true,
			"renderingMode": "3d",
			"drawOrder": "z-order",
			"useRenderCells": false,
			"blendMode": "normal",
			"zElevation": 0,
			"global": false
		},
		{
			"name": "HUD",
			"overriden": 0,
			"subLayers": [],
			"instances": [
				{
					"type": "CharactersDropdown",
					"properties": {
						"items": "",
						"tooltip": "",
						"initially-visible": true,
						"enabled": true,
						"type": "dropdown-list",
						"multi-select": false,
						"auto-font-size": true,
						"id": "dropdown",
						"class": ""
					},
					"uid": 83,
					"instanceVariables": {},
					"behaviors": {},
					"world": {
						"x": 2,
						"y": 2,
						"width": 32,
						"height": 12,
						"originX": 0,
						"originY": 0,
						"color": [
							1,
							1,
							1,
							1
						]
					}
				},
				{
					"type": "StagesDropdown",
					"properties": {
						"items": "",
						"tooltip": "",
						"initially-visible": true,
						"enabled": true,
						"type": "dropdown-list",
						"multi-select": false,
						"auto-font-size": true,
						"id": "dropdown",
						"class": ""
					},
					"uid": 23,
					"instanceVariables": {},
					"behaviors": {},
					"world": {
						"x": 2,
						"y": 18,
						"width": 32,
						"height": 12,
						"originX": 0,
						"originY": 0,
						"color": [
							1,
							1,
							1,
							1
						]
					}
				}
			],
			"sid": 824128834289631,
			"effectTypes": [],
			"isInitiallyVisible": true,
			"isInitiallyInteractive": true,
			"color": [
				1,
				1,
				1,
				1
			],
			"backgroundColor": [
				0.3686274509803922,
				0.3686274509803922,
				0.3686274509803922,
				1
			],
			"isTransparent": true,
			"parallaxX": 0,
			"parallaxY": 0,
			"scaleRate": 1,
			"forceOwnTexture": false,
			"renderingMode": "3d",
			"drawOrder": "z-order",
			"useRenderCells": false,
			"blendMode": "normal",
			"zElevation": 0,
			"global": false
		}
	],
	"sid": 295273452786145,
	"nonworld-instances": [
		{
			"type": "arr_Characters",
			"properties": {
				"width": 10,
				"height": 1,
				"depth": 1
			},
			"uid": 11,
			"instanceVariables": {}
		},
		{
			"type": "arr_StagePlacement",
			"properties": {
				"width": 10,
				"height": 1,
				"depth": 1
			},
			"uid": 31,
			"instanceVariables": {}
		},
		{
			"type": "arr_AtkFloorSide",
			"properties": {
				"width": 10,
				"height": 1,
				"depth": 1
			},
			"uid": 42,
			"instanceVariables": {}
		},
		{
			"type": "arr_AtkFloorUp",
			"properties": {
				"width": 10,
				"height": 1,
				"depth": 1
			},
			"uid": 44,
			"instanceVariables": {}
		},
		{
			"type": "arr_AtkFloorDown",
			"properties": {
				"width": 10,
				"height": 1,
				"depth": 1
			},
			"uid": 45,
			"instanceVariables": {}
		},
		{
			"type": "arr_AtkAirSide",
			"properties": {
				"width": 10,
				"height": 1,
				"depth": 1
			},
			"uid": 46,
			"instanceVariables": {}
		},
		{
			"type": "arr_AtkAirUp",
			"properties": {
				"width": 10,
				"height": 1,
				"depth": 1
			},
			"uid": 47,
			"instanceVariables": {}
		},
		{
			"type": "arr_AtkAirDown",
			"properties": {
				"width": 10,
				"height": 1,
				"depth": 1
			},
			"uid": 48,
			"instanceVariables": {}
		},
		{
			"type": "arr_AtkSpecialDown",
			"properties": {
				"width": 10,
				"height": 1,
				"depth": 1
			},
			"uid": 52,
			"instanceVariables": {}
		},
		{
			"type": "arr_AtkSpecialUp",
			"properties": {
				"width": 10,
				"height": 1,
				"depth": 1
			},
			"uid": 53,
			"instanceVariables": {}
		},
		{
			"type": "arr_Projectiles",
			"properties": {
				"width": 10,
				"height": 1,
				"depth": 1
			},
			"uid": 55,
			"instanceVariables": {}
		},
		{
			"type": "arr_HitMeshEffect",
			"properties": {
				"width": 10,
				"height": 1,
				"depth": 1
			},
			"uid": 82,
			"instanceVariables": {}
		}
	],
	"effectTypes": [],
	"width": 640,
	"height": 360,
	"unboundedScrolling": false,
	"vpX": 0.5,
	"vpY": 0.5,
	"projection": "perspective",
	"eventSheet": "eGame"
}